{
  "multipart": [
    {
      "when": {
        "facing": "down"
      },
      "apply": {
        "model": "industrialrenewal:block/entity_detector",
        "x": -90
      }
    },
    {
      "when": {
        "facing": "up"
      },
      "apply": {
        "model": "industrialrenewal:block/entity_detector",
        "x": 90
      }
    },
    {
      "when": {
        "facing": "north"
      },
      "apply": {
        "model": "industrialrenewal:block/entity_detector"
      }
    },
    {
      "when": {
        "facing": "south"
      },
      "apply": {
        "model": "industrialrenewal:block/entity_detector",
        "y": 180
      }
    },
    {
      "when": {
        "facing": "east"
      },
      "apply": {
        "model": "industrialrenewal:block/entity_detector",
        "y": 90
      }
    },
    {
      "when": {
        "facing": "west"
      },
      "apply": {
        "model": "industrialrenewal:block/entity_detector",
        "y": 270
      }
    },
    {
      "when": {
        "base": "north"
      },
      "apply": {
        "model": "industrialrenewal:block/flame_detector_base",
        "x": 90,
        "y": 180
      }
    },
    {
      "when": {
        "base": "south"
      },
      "apply": {
        "model": "industrialrenewal:block/flame_detector_base",
        "x": 90
      }
    },
    {
      "when": {
        "base": "east"
      },
      "apply": {
        "model": "industrialrenewal:block/flame_detector_base",
        "x": 90,
        "y": -90
      }
    },
    {
      "when": {
        "base": "west"
      },
      "apply": {
        "model": "industrialrenewal:block/flame_detector_base",
        "x": 90,
        "y": 90
      }
    },
    {
      "when": {
        "base": "down"
      },
      "apply": {
        "model": "industrialrenewal:block/flame_detector_base",
        "y": 180
      }
    },
    {
      "when": {
        "base": "up"
      },
      "apply": {
        "model": "industrialrenewal:block/flame_detector_base",
        "x": 180
      }
    }
  ]
}